{
    "stops": [
        {
            "name": "Svingeln",
            "coords": [
                11.991568,
                57.713244
            ]
        },
        {
            "name": "Ullevi Norra",
            "coords": [
                11.986166,
                57.7081
            ]
        },
        {
            "name": "Ullevi Södra",
            "coords": [
                11.985012,
                57.703913
            ]
        },
        {
            "name": "Scandinavium",
            "events": [
                {
                    "eventName": "Something",
                    "eventTime": "17:00"
                }
            ],
            "coords": [
                11.985886,
                57.70043
            ]
        },
        {
            "name": "Korsvägen",
            "coords": [
                11.98691,
                57.696982
            ]
        },
        {
            "name": "Liseberg Station",
            "coords": [
                11.994167,
                57.697522
            ]
        },
        {
            "name": "Sankt Sigfrids Plan",
            "coords": [
                11.999343,
                57.698648
            ]
        },
        {
            "name": "Redbergsplatsen",
            "coords": [
                12.004559,
                57.716195
            ]
        },
        {
            "name": "Olskrokstorget",
            "coords": [
                11.999052,
                57.714637
            ]
        },
        {
            "name": "Stockholmsgatan",
            "coords": [
                12.013843,
                57.717086
            ]
        },
        {
            "name": "Härlanda",
            "coords": [
                12.019761,
                57.71817
            ]
        },
        {
            "name": "Solrosgatan",
            "coords": [
                12.025096,
                57.716403
            ]
        },
        {
            "name": "Sanatoriegatan",
            "coords": [
                12.024113,
                57.713416
            ]
        },
        {
            "name": "Virginsgatan",
            "coords": [
                12.023512,
                57.711046
            ]
        },
        {
            "name": "Welandergatan",
            "coords": [
                12.024004,
                57.705949
            ]
        },
        {
            "name": "Töpelsgatan",
            "coords": [
                12.022278,
                57.702418
            ]
        },
        {
            "name": "Bögatan",
            "coords": [
                12.016223,
                57.701028
            ]
        },
        {
            "name": "Ekmanska",
            "coords": [
                12.009405,
                57.699646
            ]
        },
        {
            "name": "Bäckeliden",
            "coords": [
                12.003551,
                57.699909
            ]
        }
    ],
    "styles": [
        {
            "type": "TRAM",
            "lineNumber": "3",
            "color": "rgb(255, 255, 255)",
            "backgroundColor": "rgb(0, 113, 193)"
        },
        {
            "type": "TRAM",
            "lineNumber": "5",
            "color": "rgb(255, 255, 255)",
            "backgroundColor": "rgb(198, 53, 57)"
        },
        {
            "type": "TRAM",
            "lineNumber": "8",
            "color": "rgb(255, 255, 255)",
            "backgroundColor": "rgb(165, 68, 154)"
        },
        {
            "type": "TRAM",
            "lineNumber": "6",
            "color": "rgb(0, 67, 92)",
            "backgroundColor": "rgb(248, 152, 40)"
        }
    ],
    "paths": [
        {
            "type": [
                "TRAM"
            ],
            "from": "Svingeln",
            "to": "Ullevi Norra",
            "coords": [
                [
                    11.990822,
                    57.712588
                ],
                [
                    11.990634,
                    57.71217
                ]
            ]
        }
    ],
    "lines": [
        {
            "number": "8",
            "name": "Mot Frölunda",
            "startTimes": [
                "06:18",
                "06:41",
                "06:59",
                "07:27",
                "07:34",
                "07:59",
                "08:25",
                "10:03",
                "10:43",
                "11:03",
                "11:33",
                "12:13",
                "12:43",
                "13:43",
                "14:04",
                "14:43",
                "15:14",
                "15:40",
                "16:08",
                "16:36",
                "17:00",
                "17:20",
                "17:48",
                "18:26",
                "18:59",
                "19:35",
                "20:35",
                "21:35",
                "22:35",
                "23:35"
            ],
            "stops": [
                "Svingeln",
                "Ullevi Norra",
                "Ullevi Södra",
                "Scandinavium",
                "Korsvägen"
            ]
        },
        {
            "number": "5",
            "name": "Mot Östra Sjukhuset",
            "startTimes": [
                "00:30",
                "17:18"
            ],
            "stops": [
                "Korsvägen",
                "Liseberg Station",
                "Sankt Sigfrids Plan"
            ]
        },
        {
            "number": "3",
            "name": "Mot Kålltorp",
            "startTimes": [
                "00:00",
                "17:04"
            ],
            "stops": [
                "Svingeln",
                "Olskrokstorget",
                "Redbergsplatsen",
                "Stockholmsgatan",
                "Härlanda",
                "Solrosgatan",
                "Sanatoriegatan",
                "Virginsgatan"
            ]
        },
        {
            "number": "5",
            "name": "Mot Länsmansgården",
            "startTimes": [
                "00:30",
                "17:19"
            ],
            "stops": [
                "Virginsgatan",
                "Welandergatan",
                "Töpelsgatan",
                "Bögatan",
                "Ekmanska",
                "Bäckeliden",
                "Sankt Sigfrids Plan"
            ]
        },
        {
            "number": "6",
            "name": "Mot Länsmansgården via Sahlgrenska",
            "startTimes": [
                "16:41",
                "16:51",
                "16:59",
                "17:08",
                "17:16",
                "17:36"
            ],
            "stops": [
                "Svingeln",
                "Ullevi Norra",
                "Ullevi Södra",
                "Scandinavium",
                "Korsvägen"
            ]
        }
    ]
}